naramarket_mcp/__init__.py
naramarket_mcp/__main__.py
naramarket_mcp/server.py
naramarket_mcp-0.1.2.dist-info/METADATA
naramarket_mcp-0.1.2.dist-info/WHEEL
naramarket_mcp-0.1.2.dist-info/entry_points.txt
naramarket_mcp-0.1.2.dist-info/RECORD
