Metadata-Version: 2.4
Name: naramarket-mcp
Version: 0.1.2
Summary: 나라장터 입찰 공고 검색을 위한 MCP 서버
Requires-Python: >=3.11
Requires-Dist: httpx>=0.28.1
Requires-Dist: mcp[cli]>=1.9.0
Requires-Dist: python-dotenv>=1.1.0
